{"_type":"export","__export_format":4,"__export_date":"2020-06-06T23:02:03.367Z","__export_source":"insomnia.desktop.app:v7.1.1","resources":[{"_id":"req_3c8ba74943874474b3c24f2a23679323","authentication":{},"body":{},"created":1591484503093,"description":"","headers":[],"isPrivate":false,"metaSortKey":-1591484503093,"method":"GET","modified":1591484507911,"name":"test","parameters":[],"parentId":"wrk_2784aabfdf264db594f0fef076d19a8f","settingDisableRenderRequestBody":false,"settingEncodeUrl":true,"settingFollowRedirects":"global","settingRebuildPath":true,"settingSendCookies":true,"settingStoreCookies":true,"url":"{{ uri  }}","_type":"request"},{"_id":"wrk_2784aabfdf264db594f0fef076d19a8f","created":1591469805555,"description":"","modified":1591469815515,"name":"NLW - 1.0","parentId":null,"_type":"workspace"},{"_id":"env_b60112e3604129df6be92f6bc8278a6d205aadac","color":null,"created":1591469805908,"data":{"routes":{"users":"users"},"uri":"{{ url  }}/{{ version  }}","url":"localhost:3000","version":"v1"},"dataPropertyOrder":{"&":["uri","url","version","routes"],"&~|routes":["users"]},"isPrivate":false,"metaSortKey":1591469805908,"modified":1591469971496,"name":"Base Environment","parentId":"wrk_2784aabfdf264db594f0fef076d19a8f","_type":"environment"},{"_id":"jar_b60112e3604129df6be92f6bc8278a6d205aadac","cookies":[],"created":1591469805931,"modified":1591469805931,"name":"Default Jar","parentId":"wrk_2784aabfdf264db594f0fef076d19a8f","_type":"cookie_jar"}]}